{"singlePage": [], "startSite": "", "filingNum": "", "onePageListNum": 15, "commentLabelColor": "#006b75", "yearColorList": ["#bc4c00", "#0969da", "#1f883d", "#A333D0"], "i18n": "CN", "themeMode": "manual", "dayTheme": "light", "nightTheme": "dark", "urlMode": "pinyin", "script": "", "style": "", "head": "", "indexScript": "", "indexStyle": "", "bottomText": "", "showPostSource": 1, "iconList": {}, "UTC": 8, "rssSplit": "sentence", "exlink": {}, "needComment": 1, "allHead": "", "title": "\u6c64\u5706\u6c81-Xiaoyuan7021\u7684\u535a\u5ba2", "subTitle": "\u6211\u662fXiaoyuan7021\uff0c\u4e00\u540dMC\u533a\u7684\u5c0fUP\u4e3b\uff0c\u5e73\u65f6\u559c\u6b22\u5206\u4eab\u4e00\u4e9bMC\u6559\u7a0b\u548c2B2T\u6e38\u73a9\u89c6\u9891", "avatarUrl": "https://pic2.zhimg.com/v2-8a372f4f12ab6fbe8eeb6482fbe998fc_r.jpg?source=1940ef5c", "GMEEK_VERSION": "last", "postListJson": {}, "singeListJson": {}, "labelColorDict": {"bug": "#d73a4a", "documentation": "#0075ca", "duplicate": "#cfd3d7", "enhancement": "#a2eeef", "good first issue": "#7057ff", "help wanted": "#008672", "invalid": "#e4e669", "MC": "#8d83f8", "Other": "#9e298c", "question": "#d876e3", "wontfix": "#ffffff", "Zoho": "#3ca1dc"}, "displayTitle": "\u6c64\u5706\u6c81-Xiaoyuan7021\u7684\u535a\u5ba2", "faviconUrl": "https://pic2.zhimg.com/v2-8a372f4f12ab6fbe8eeb6482fbe998fc_r.jpg?source=1940ef5c", "ogImage": "https://pic2.zhimg.com/v2-8a372f4f12ab6fbe8eeb6482fbe998fc_r.jpg?source=1940ef5c", "primerCSS": "<link href='https://mirrors.sustech.edu.cn/cdnjs/ajax/libs/Primer/21.0.7/primer.css' rel='stylesheet' />", "homeUrl": "https://Xiaoyuan7021.github.io", "prevUrl": "disabled", "nextUrl": "disabled"}